Rails5KaifaJinjieBeta/README.md
Rails5KaifaJinjieBeta/__init__.py
Rails5KaifaJinjieBeta/__main__.py
Rails5KaifaJinjieBeta/file.epub
Rails5KaifaJinjieBeta/index.html
Rails5KaifaJinjieBeta/css/__init__.py
Rails5KaifaJinjieBeta/css/annotations.css
Rails5KaifaJinjieBeta/css/main.css
Rails5KaifaJinjieBeta/css/normalize.css
Rails5KaifaJinjieBeta/css/popup.css
Rails5KaifaJinjieBeta/font/__init__.py
Rails5KaifaJinjieBeta/font/fontello.eot
Rails5KaifaJinjieBeta/font/fontello.svg
Rails5KaifaJinjieBeta/font/fontello.ttf
Rails5KaifaJinjieBeta/font/fontello.woff
Rails5KaifaJinjieBeta/img/__init__.py
Rails5KaifaJinjieBeta/img/annotator-glyph-sprite.png
Rails5KaifaJinjieBeta/img/annotator-icon-sprite.png
Rails5KaifaJinjieBeta/img/apple-touch-icon.png
Rails5KaifaJinjieBeta/img/cancelfullscreen.png
Rails5KaifaJinjieBeta/img/close.png
Rails5KaifaJinjieBeta/img/fullscreen.png
Rails5KaifaJinjieBeta/img/loader.gif
Rails5KaifaJinjieBeta/img/menu-icon.png
Rails5KaifaJinjieBeta/img/save.png
Rails5KaifaJinjieBeta/img/saved.png
Rails5KaifaJinjieBeta/img/settings-s.png
Rails5KaifaJinjieBeta/img/settings.png
Rails5KaifaJinjieBeta/img/star.png
Rails5KaifaJinjieBeta/js/__init__.py
Rails5KaifaJinjieBeta/js/epub.js
Rails5KaifaJinjieBeta/js/epub.min.js
Rails5KaifaJinjieBeta/js/epub.min.map
Rails5KaifaJinjieBeta/js/hooks.min.js
Rails5KaifaJinjieBeta/js/hooks.min.map
Rails5KaifaJinjieBeta/js/reader.js
Rails5KaifaJinjieBeta/js/reader.js.map
Rails5KaifaJinjieBeta/js/reader.min.js
Rails5KaifaJinjieBeta/js/reader.min.map
Rails5KaifaJinjieBeta/js/hooks/__init__.py
Rails5KaifaJinjieBeta/js/hooks/extensions/__init__.py
Rails5KaifaJinjieBeta/js/hooks/extensions/highlight.js
Rails5KaifaJinjieBeta/js/libs/__init__.py
Rails5KaifaJinjieBeta/js/libs/jquery.min.js
Rails5KaifaJinjieBeta/js/libs/localforage.min.js
Rails5KaifaJinjieBeta/js/libs/screenfull.js
Rails5KaifaJinjieBeta/js/libs/screenfull.min.js
Rails5KaifaJinjieBeta/js/libs/zip.min.js
Rails5KaifaJinjieBeta/js/plugins/__init__.py
rails_5_kaifa_jinjie_beta-2024.3.2.0.dist-info/METADATA
rails_5_kaifa_jinjie_beta-2024.3.2.0.dist-info/WHEEL
rails_5_kaifa_jinjie_beta-2024.3.2.0.dist-info/entry_points.txt
rails_5_kaifa_jinjie_beta-2024.3.2.0.dist-info/top_level.txt
rails_5_kaifa_jinjie_beta-2024.3.2.0.dist-info/RECORD
